gen_gtkmm/__init__.py
gen_gtkmm/py.typed
gen_gtkmm/conf/gen_gtkmm.cfg
gen_gtkmm/conf/gen_gtkmm.logo
gen_gtkmm/conf/gen_gtkmm_util.cfg
gen_gtkmm/conf/project.yaml
gen_gtkmm/conf/template/gtkmm3/Makefile.template
gen_gtkmm/conf/template/gtkmm3/about_header.template
gen_gtkmm/conf/template/gtkmm3/about_source.template
gen_gtkmm/conf/template/gtkmm3/application_header.template
gen_gtkmm/conf/template/gtkmm3/application_source.template
gen_gtkmm/conf/template/gtkmm3/csflags.template
gen_gtkmm/conf/template/gtkmm3/cxxflags.template
gen_gtkmm/conf/template/gtkmm3/help_header.template
gen_gtkmm/conf/template/gtkmm3/help_source.template
gen_gtkmm/conf/template/gtkmm3/home_header.template
gen_gtkmm/conf/template/gtkmm3/home_source.template
gen_gtkmm/conf/template/gtkmm3/imodel_header.template
gen_gtkmm/conf/template/gtkmm3/main_source.template
gen_gtkmm/conf/template/gtkmm3/model_header.template
gen_gtkmm/conf/template/gtkmm3/model_source.template
gen_gtkmm/conf/template/gtkmm3/objects.template
gen_gtkmm/conf/template/gtkmm3/odflags.template
gen_gtkmm/conf/template/gtkmm3/settings_header.template
gen_gtkmm/conf/template/gtkmm3/settings_source.template
gen_gtkmm/conf/template/gtkmm3/sources.template
gen_gtkmm/conf/template/gtkmm3/toolchain.template
gen_gtkmm/conf/template/gtkmm4/Makefile.template
gen_gtkmm/conf/template/gtkmm4/about_header.template
gen_gtkmm/conf/template/gtkmm4/about_source.template
gen_gtkmm/conf/template/gtkmm4/application_header.template
gen_gtkmm/conf/template/gtkmm4/application_source.template
gen_gtkmm/conf/template/gtkmm4/csflags.template
gen_gtkmm/conf/template/gtkmm4/cxxflags.template
gen_gtkmm/conf/template/gtkmm4/help_header.template
gen_gtkmm/conf/template/gtkmm4/help_source.template
gen_gtkmm/conf/template/gtkmm4/home_header.template
gen_gtkmm/conf/template/gtkmm4/home_source.template
gen_gtkmm/conf/template/gtkmm4/imodel_header.template
gen_gtkmm/conf/template/gtkmm4/main_source.template
gen_gtkmm/conf/template/gtkmm4/model_header.template
gen_gtkmm-1.1.6.dist-info/LICENSE
gen_gtkmm-1.1.6.dist-info/METADATA
gen_gtkmm-1.1.6.dist-info/WHEEL
gen_gtkmm-1.1.6.dist-info/top_level.txt
gen_gtkmm-1.1.6.dist-info/RECORD
